{
  "course": {
    "title": "Universal Digital Artistry Foundations",
    "subtitle": "Software-Independent Digital Painting Course",
    "description": "Master digital art fundamentals that work across all major painting software including Krita, Photoshop, Procreate, Painter, PaintStorm Studio, and more. Learn universal concepts, techniques, and workflows that transcend any single application.",
    "author": {
      "name": "Digital Artistry Course",
      "email": "contact@digitalartistry.course",
      "website": "https://digitalartistry.course",
      "bio": "Comprehensive digital art education focused on universal principles and cross-platform skills"
    },
    "version": "1.0.0",
    "lastUpdated": "2024-10-14",
    "language": "en",
    "difficulty": "beginner",
    "estimatedHours": 25,
    "tags": ["digital art", "digital painting", "krita", "photoshop", "procreate", "painter", "brush techniques", "color theory", "layers", "software independent"]
  },
  
  "branding": {
    "primaryColor": "#667eea",
    "secondaryColor": "#f8fafc",
    "accentColor": "#764ba2",
    "fontFamily": "Trebuchet MS, Arial, sans-serif",
    "logo": "images/logo.png",
    "favicon": "favicon.ico"
  },
  
  "navigation": {
    "showBreadcrumbs": true,
    "showProgressBar": true,
    "showLessonNav": true,
    "showSearch": true,
    "showThemeToggle": true,
    "keyboardShortcuts": true
  },
  
  "modules": [
    {
      "id": "module-1",
      "title": "Foundation Module",
      "description": "Essential digital art concepts that work across all software",
      "icon": "🚀",
      "color": "#f5576c",
      "lessons": [
        {
          "id": "lesson-1-1",
          "title": "Welcome to Digital Artistry",
          "filename": "welcome_digital_art.html",
          "duration": "15 minutes",
          "difficulty": "beginner",
          "description": "Introduction to digital art, what makes it unique, and what you'll learn"
        },
        {
          "id": "lesson-1-2",
          "title": "Understanding Your Digital Canvas",
          "filename": "digital_canvas_basics.html",
          "duration": "30 minutes",
          "difficulty": "beginner",
          "description": "Resolution, canvas size, color modes, and file formats across all software"
        },
        {
          "id": "lesson-1-3",
          "title": "Interface Fundamentals",
          "filename": "interface_fundamentals.html",
          "duration": "40 minutes",
          "difficulty": "beginner",
          "description": "Universal interface concepts and navigation patterns in digital art software"
        },
        {
          "id": "lesson-1-4",
          "title": "Essential Digital Tools",
          "filename": "essential_digital_tools.html",
          "duration": "45 minutes",
          "difficulty": "beginner",
          "description": "Selection, transform, move, and other universal tools across platforms"
        }
      ]
    },
    {
      "id": "module-2",
      "title": "Core Skills Module",
      "description": "Build your digital painting foundation with universal techniques",
      "icon": "🎨",
      "color": "#4facfe",
      "lessons": [
        {
          "id": "lesson-2-1",
          "title": "Brush Theory & Dynamics",
          "filename": "brush_theory.html",
          "duration": "50 minutes",
          "difficulty": "beginner",
          "description": "Understanding digital brushes, pressure sensitivity, and dynamics across all apps"
        },
        {
          "id": "lesson-2-2",
          "title": "Layer Workflows & Compositing",
          "filename": "layer_workflows.html",
          "duration": "45 minutes",
          "difficulty": "beginner",
          "description": "Mastering layers, blend modes, and non-destructive editing techniques"
        },
        {
          "id": "lesson-2-3",
          "title": "Color Science for Digital Artists",
          "filename": "color_science.html",
          "duration": "55 minutes",
          "difficulty": "intermediate",
          "description": "Color theory, digital color mixing, and creating harmonious palettes"
        },
        {
          "id": "lesson-2-4",
          "title": "Masking & Selection Techniques",
          "filename": "masking_selection.html",
          "duration": "40 minutes",
          "difficulty": "intermediate",
          "description": "Advanced selection methods and mask-based workflows"
        }
      ]
    },
    {
      "id": "module-3",
      "title": "Technique Module",
      "description": "Professional digital painting workflows and techniques",
      "icon": "🖼️",
      "color": "#43e97b",
      "lessons": [
        {
          "id": "lesson-3-1",
          "title": "Digital Painting Workflow",
          "filename": "painting_workflow.html",
          "duration": "60 minutes",
          "difficulty": "intermediate",
          "description": "Complete process from sketch to finished artwork across any software"
        },
        {
          "id": "lesson-3-2",
          "title": "Lighting & Form Fundamentals",
          "filename": "lighting_form.html",
          "duration": "50 minutes",
          "difficulty": "intermediate",
          "description": "Understanding and rendering light, shadow, and three-dimensional form"
        },
        {
          "id": "lesson-3-3",
          "title": "Texture & Detail Techniques",
          "filename": "texture_detail.html",
          "duration": "45 minutes",
          "difficulty": "intermediate",
          "description": "Creating realistic and stylized textures digitally"
        },
        {
          "id": "lesson-3-4",
          "title": "File Management & Export",
          "filename": "file_management.html",
          "duration": "30 minutes",
          "difficulty": "beginner",
          "description": "Organizing, saving, and exporting your artwork professionally"
        }
      ]
    },
    {
      "id": "module-4",
      "title": "Advanced Topics",
      "description": "Professional techniques and cross-software workflows",
      "icon": "⚡",
      "color": "#f093fb",
      "lessons": [
        {
          "id": "lesson-4-1",
          "title": "Advanced Brush Customization",
          "filename": "advanced_brushes.html",
          "duration": "50 minutes",
          "difficulty": "advanced",
          "description": "Creating and fine-tuning custom brushes for your unique style"
        },
        {
          "id": "lesson-4-2",
          "title": "Speed Painting Techniques",
          "filename": "speed_painting.html",
          "duration": "45 minutes",
          "difficulty": "advanced",
          "description": "Efficient workflows and shortcuts for faster painting"
        },
        {
          "id": "lesson-4-3",
          "title": "Software Comparison & Migration",
          "filename": "software_comparison.html",
          "duration": "40 minutes",
          "difficulty": "intermediate",
          "description": "Detailed comparison and tips for switching between applications"
        },
        {
          "id": "lesson-4-4",
          "title": "Troubleshooting Common Issues",
          "filename": "troubleshooting.html",
          "duration": "35 minutes",
          "difficulty": "beginner",
          "description": "Solutions to universal digital art challenges and technical problems"
        }
      ]
    }
  ],
  
  "prerequisites": [
    "Basic computer literacy",
    "A graphics tablet with pressure sensitivity (highly recommended)",
    "One or more digital painting applications installed (Krita, Photoshop, Procreate, Painter, PaintStorm Studio, etc.)",
    "Willingness to practice and experiment",
    "No prior art experience required!"
  ],
  
  "learningObjectives": [
    "Understand fundamental digital art concepts that apply to all software",
    "Master brush dynamics, pressure sensitivity, and digital mark-making",
    "Create professional artwork using layers, masks, and blend modes",
    "Apply color theory to create harmonious and impactful artwork",
    "Develop efficient workflows that work across multiple applications",
    "Build confidence in your digital artistry regardless of software choice"
  ],
  
  "supportedSoftware": [
    {
      "name": "Krita",
      "free": true,
      "platforms": ["Windows", "macOS", "Linux"],
      "url": "https://krita.org"
    },
    {
      "name": "Adobe Photoshop",
      "free": false,
      "platforms": ["Windows", "macOS"],
      "url": "https://www.adobe.com/products/photoshop.html"
    },
    {
      "name": "Procreate",
      "free": false,
      "platforms": ["iPad"],
      "url": "https://procreate.art"
    },
    {
      "name": "Corel Painter",
      "free": false,
      "platforms": ["Windows", "macOS"],
      "url": "https://www.painterartist.com"
    },
    {
      "name": "PaintStorm Studio",
      "free": false,
      "platforms": ["Windows", "macOS", "Linux"],
      "url": "https://paintstormstudio.com"
    },
    {
      "name": "Clip Studio Paint",
      "free": false,
      "platforms": ["Windows", "macOS", "iPad", "Android"],
      "url": "https://www.clipstudio.net"
    },
    {
      "name": "Affinity Photo",
      "free": false,
      "platforms": ["Windows", "macOS", "iPad"],
      "url": "https://affinity.serif.com/photo"
    }
  ],
  
  "resources": {
    "documentation": [
      {
        "title": "Krita Documentation",
        "url": "https://docs.krita.org",
        "description": "Official Krita user manual and tutorials"
      },
      {
        "title": "Adobe Photoshop Learn & Support",
        "url": "https://helpx.adobe.com/photoshop/tutorials.html",
        "description": "Official Adobe tutorials and documentation"
      },
      {
        "title": "Procreate Handbook",
        "url": "https://procreate.art/handbook",
        "description": "Complete Procreate user guide"
      }
    ],
    "communities": [
      {
        "name": "r/DigitalPainting",
        "platform": "Reddit",
        "url": "https://reddit.com/r/DigitalPainting",
        "description": "Active community for digital artists"
      },
      {
        "name": "Krita Artists",
        "platform": "Forum",
        "url": "https://krita-artists.org",
        "description": "Official Krita community forum"
      },
      {
        "name": "ConceptArt.org",
        "platform": "Forum",
        "url": "https://conceptart.org",
        "description": "Professional concept art community"
      }
    ],
    "books": [
      {
        "title": "Color and Light: A Guide for the Realist Painter",
        "author": "James Gurney",
        "isbn": "978-0740797712",
        "description": "Essential color theory for artists"
      },
      {
        "title": "Drawing on the Right Side of the Brain",
        "author": "Betty Edwards",
        "isbn": "978-1585429202",
        "description": "Fundamental drawing and observation skills"
      }
    ],
    "tools": [
      {
        "name": "Adobe Color",
        "url": "https://color.adobe.com",
        "description": "Color palette generator and explorer"
      },
      {
        "name": "Coolors",
        "url": "https://coolors.co",
        "description": "Fast color scheme generator"
      },
      {
        "name": "PureRef",
        "url": "https://www.pureref.com",
        "description": "Reference image organizer for artists"
      }
    ]
  },
  
  "assessment": {
    "quizzes": true,
    "exercises": true,
    "projects": true,
    "certification": false,
    "passingScore": 80
  },
  
  "features": {
    "codeHighlighting": false,
    "copyCodeButton": false,
    "progressTracking": true,
    "offlineSupport": false,
    "responsiveDesign": true,
    "accessibility": true,
    "printFriendly": true,
    "searchEnabled": true,
    "analytics": true,
    "softwareComparison": true,
    "interactiveDemos": true
  },
  
  "seo": {
    "metaDescription": "Learn digital art with this comprehensive software-independent course. Master techniques that work in Krita, Photoshop, Procreate, Painter, and all major digital painting applications.",
    "keywords": ["digital art", "digital painting", "learn digital art", "krita tutorial", "photoshop painting", "procreate tutorial", "brush techniques", "color theory", "layers tutorial", "digital art beginner"],
    "ogImage": "images/og-image.png",
    "twitterCard": "summary_large_image"
  },
  
  "deployment": {
    "baseUrl": "/",
    "gaTrackingId": "",
    "disqusShortname": "",
    "githubRepo": ""
  },
  
  "projectLocations": {
    "mainProject": "\\wsl.localhost\\Ubuntu\\home\\practicalace\\projects\\digitalarts",
    "referenceProjects": [
      "\\wsl.localhost\\Ubuntu\\home\\practicalace\\projects\\paintstorm",
      "\\wsl.localhost\\Ubuntu\\home\\practicalace\\projects\\paintstorm_int",
      "\\wsl.localhost\\Ubuntu\\home\\practicalace\\projects\\paintstorm_adv"
    ],
    "notes": "Reference projects contain PaintStorm-specific content that can be adapted for universal course lessons"
  },
  
  "lessonCreationProcess": {
    "overview": "Lessons are created incrementally using a fragment-based approach. Each lesson is broken into multiple HTML fragments (a, b, c, d, etc.) that are later concatenated into a complete lesson file. This allows for iterative review and correction during the creation process.",
    
    "fragmentWorkflow": {
      "description": "The creation process follows a strict iterative cycle",
      "steps": [
        "1. AI creates fragment A (e.g., parts/lesson_name_a.html)",
        "2. AI STOPS and waits for human review",
        "3. Human reviews fragment A and provides feedback/corrections",
        "4. AI makes any requested edits to fragment A",
        "5. Human approves fragment A",
        "6. AI creates fragment B",
        "7. Repeat steps 2-6 for fragments C, D, E, etc. until lesson is complete",
        "8. Concatenate all fragments into final lesson file"
      ],
      "criticalRules": [
        "NEVER create multiple fragments without explicit approval",
        "ALWAYS stop after creating each fragment",
        "ALWAYS wait for human review before proceeding",
        "EDIT existing fragments when changes are needed, don't rewrite",
        "Ask for clarification if instructions are unclear"
      ]
    },
    
    "fragmentGuidelines": {
      "size": {
        "description": "Each fragment should be manageable in size",
        "guidelines": [
          "Typically 300-800 lines of HTML",
          "1-3 major sections per fragment",
          "Not so large that review becomes overwhelming",
          "Not so small that you have 20+ fragments",
          "Break at logical content boundaries"
        ]
      },
      "namingConvention": {
        "pattern": "parts/{lesson_filename}_{letter}.html",
        "examples": [
          "parts/layer_workflows_a.html",
          "parts/layer_workflows_b.html",
          "parts/brush_fundamentals_a.html"
        ],
        "rules": [
          "Use underscores, not hyphens or spaces",
          "Lowercase only",
          "Letter suffix (a, b, c, d, etc.) indicates fragment sequence",
          "Filename matches the lesson's main filename from course-config.json"
        ]
      },
      "contentStructure": {
        "fragmentA": {
          "description": "First fragment includes full HTML document setup",
          "mustInclude": [
            "<!DOCTYPE html> declaration",
            "Complete <head> with meta tags, title, CSS links",
            "Mermaid script import in <head>",
            "Favicon link: <link rel='icon' type='image/png' href='/favicon.png'>",
            "<body> opening tag",
            "Skip-to-content link for accessibility",
            "Progress indicator",
            "Full navigation bar",
            "Breadcrumb navigation",
            "<main id='main-content'> opening",
            "Container div",
            "Lesson header with title and lead paragraph",
            "Learning objectives card",
            "Universal approach card (showing supported software)",
            "Table of Contents with all major sections",
            "First 1-3 major content sections",
            "Comment indicating end of fragment A"
          ]
        },
        "fragmentBtoN": {
          "description": "Middle fragments contain main content sections",
          "mustInclude": [
            "Comment indicating start of fragment (e.g., <!-- PART B STARTS HERE -->)",
            "2-4 major content sections",
            "Appropriate subsections, examples, and interactive demos",
            "Comment indicating end of fragment"
          ],
          "mustNotInclude": [
            "HTML doctype or head elements",
            "Body, nav, or structural opening tags",
            "Any duplicate navigation or headers"
          ]
        },
        "finalFragment": {
          "description": "Last fragment includes closing elements",
          "mustInclude": [
            "Comment indicating start of final fragment",
            "Final content sections",
            "Summary section with key takeaways",
            "Additional resources section",
            "What's next section",
            "Lesson navigation (prev/next links)",
            "Closing </main> tag",
            "Footer",
            "JavaScript includes (clipboard.js, course-enhancements.js)",
            "Closing </body> and </html> tags"
          ]
        }
      }
    },
    
    "contentRequirements": {
      "tone": {
        "description": "Write as an amazing instructor teaching new learners",
        "characteristics": [
          "Friendly and accessible",
          "Encouraging and supportive",
          "Clear and concise",
          "Use conversational language",
          "Include personality and enthusiasm",
          "Make complex topics approachable"
        ]
      },
      "softwareAgnostic": {
        "description": "Content must work across ALL major digital art software",
        "approach": [
          "Teach universal concepts first",
          "Explain the underlying principle, not specific buttons",
          "When showing software-specific info, include multiple programs",
          "Use comparison tables for software differences",
          "Focus on 'what' and 'why', not just 'how' in one app"
        ],
        "supportedSoftware": [
          "Adobe Photoshop",
          "Krita (free)",
          "Procreate (iPad)",
          "Clip Studio Paint",
          "Corel Painter",
          "PaintStorm Studio",
          "Affinity Photo"
        ]
      },
      "visualElements": {
        "mermaidDiagrams": {
          "when": "Use for workflows, hierarchies, relationships, processes",
          "requirement": "Must include mermaid script in head",
          "script": "<script type='module'>\n  import mermaid from 'https://cdn.jsdelivr.net/npm/mermaid@10/dist/mermaid.esm.min.mjs';\n  mermaid.initialize({ startOnLoad: true });\n</script>",
          "formatting": "Ensure proper escaping of special characters in mermaid syntax",
          "CRITICAL_CLOSING_TAG": "Use </div> NOT </mermaid> - mermaid diagrams are <div class='mermaid'>...</div>"
        },
        "canvasInteractive": {
          "when": "Use for interactive demos, visual demonstrations, hands-on examples",
          "requirements": [
            "Each canvas must have unique ID",
            "Include touch support for mobile",
            "Handle high DPI displays",
            "Include clear instructions for user interaction",
            "Provide fallback text if canvas doesn't work"
          ]
        },
        "svgGraphics": {
          "when": "Use for scalable illustrations, icons, diagrams",
          "benefit": "Vector graphics scale perfectly on all devices"
        },
        "emojis": {
          "when": "Use throughout for visual interest and clarity",
          "examples": "🎨 for art topics, 💡 for tips, ⚠️ for warnings, 🎯 for objectives"
        }
      },
      "examples": {
        "description": "Include plenty of real-world examples",
        "types": [
          "Practical use cases",
          "Analogies and metaphors",
          "Step-by-step demonstrations",
          "Before/after comparisons",
          "Common scenarios artists face"
        ]
      },
      "codeAndSamples": {
        "htmlSamples": "Must be properly escaped using HTML entities",
        "codeBlocks": "Wrap in <pre><code>...</code></pre>",
        "noPlaceholders": "Never use [placeholder] or [TODO] - write complete content"
      }
    },
    
    "structuralElements": {
      "requiredSections": [
        "Learning Objectives (at start)",
        "Table of Contents (collapsible)",
        "Main content sections (numbered)",
        "Summary/Key Takeaways (at end)",
        "Additional Resources (at end)",
        "What's Next (at end)"
      ],
      "organizationalTools": [
        "Cards (div.card) for important information",
        "Blockquotes for tips, warnings, insights",
        "Tables for comparisons and structured data",
        "Lists (ul/ol) for steps and bullet points",
        "Headings (h2, h3, h4) for hierarchy"
      ],
      "accessibility": [
        "Skip to content link",
        "Proper heading hierarchy",
        "Alt text for images",
        "ARIA labels where appropriate",
        "Keyboard navigation support",
        "Sufficient color contrast"
      ]
    },
    
    "technicalRequirements": {
      "mobileFriendly": {
        "description": "All content must work perfectly on mobile devices",
        "requirements": [
          "Responsive design",
          "Touch-friendly interactive elements",
          "Readable text sizes",
          "No horizontal scrolling",
          "Properly sized tap targets"
        ]
      },
      "fileLinks": {
        "favicon": "Always link to /favicon.png",
        "css": "Link to styles/main.css",
        "javascript": "Link to js/clipboard.js and js/course-enhancements.js",
        "images": "Use images/ directory for lesson images"
      },
      "htmlFormatting": {
        "doctype": "Always use <!DOCTYPE html>",
        "indentation": "Use consistent indentation (4 spaces)",
        "noNumbers": "Do NOT number headings (e.g., write 'Understanding Layers' not '1. Understanding Layers')",
        "titleFormat": "Titles may include spaces; filenames use underscores only"
      }
    },
    
    "progressTracking": {
      "description": "Update course-config.json as lessons are completed",
      "whenToUpdate": [
        "After each fragment is approved",
        "When starting a new lesson",
        "When completing a lesson"
      ],
      "whatToTrack": [
        "lessonDetails.{lesson_name}.status (not_started, in_progress, complete)",
        "lessonDetails.{lesson_name}.fragments.completed (array of finished fragments)",
        "lessonDetails.{lesson_name}.fragments.inProgress (current fragment being worked on)",
        "lessonDetails.{lesson_name}.fragments.total (total number of fragments when complete)"
      ]
    },
    
    "qualityStandards": {
      "beforeSubmitting": [
        "Verify all HTML is valid and properly nested",
        "Check that all IDs are unique",
        "Ensure all interactive demos have clear instructions",
        "Confirm software-agnostic language throughout",
        "Verify no placeholder text remains",
        "Check that all special characters are properly escaped",
        "Ensure mermaid diagrams are properly formatted",
        "Confirm mobile-friendly design elements"
      ],
      "contentQuality": [
        "Information is accurate and up-to-date",
        "Explanations are clear and beginner-friendly",
        "Examples are relevant and practical",
        "Tone is consistent and encouraging",
        "Content flows logically",
        "Sufficient detail without overwhelming"
      ]
    },
    
    "exampleFragmentFiles": {
      "reference": "See existing fragments as templates",
      "locations": [
        "parts/brush_fundamentals_a.html (complete first fragment with all setup)",
        "parts/brush_fundamentals_b.html (middle fragment with content only)",
        "parts/brush_fundamentals_c.html (another middle fragment)",
        "parts/brush_fundamentals_d.html (final fragment with closing elements)"
      ]
    }
  },
  
  "htmlStructureReference": {
    "description": "CRITICAL: All lessons must follow this exact HTML structure from existing complete lessons",
    "referenceFiles": ["painting_workflow.html", "lighting_form.html", "texture_detail.html", "layer_workflows.html"],
    "keyStructuralElements": {
      "doctype": "<!DOCTYPE html>",
      "titleFormat": "Lesson Title - Universal Digital Art Course",
      "metaTags": "<meta name='description'>, <meta name='author' content='Digital Artistry Course'>",
      "cssLink": "<link rel='stylesheet' href='styles/main.css'>",
      "faviconLink": "<link rel='icon' type='image/png' href='/favicon.png'>",
      "mermaidScript": "<script type='module'>import mermaid from CDN; mermaid.initialize({ startOnLoad: true });</script>"
    },
    "bodyOpeningStructure": {
      "skipLink": "<a href='#main-content' class='skip-to-main'>Skip to main content</a>",
      "progressBar": "<div class='progress-indicator' role='progressbar' aria-label='Page scroll progress'><div class='progress-bar'></div></div>",
      "navigation": "<nav><div class='nav-container'><a href='index.html' class='nav-logo'>🎨 Digital Artistry</a><button id='mobile-menu-toggle'>☰</button><div class='nav-links'><a href='index.html'>Home</a><a href='index.html#modules'>All Lessons</a><button id='theme-toggle'>🌙</button></div></div></nav>",
      "breadcrumb": "<nav class='breadcrumb' aria-label='Breadcrumb'><ul><li><a href='index.html'>Home</a></li><li><a href='index.html#modules'>Module Name</a></li><li aria-current='page'>Lesson Title</li></ul></nav>",
      "mainWrapper": "<main id='main-content'><div class='container'>"
    },
    "lessonHeaderStructure": {
      "headerOpen": "<header>",
      "mainTitle": "<h1>📚 Emoji Icon + Title</h1>",
      "leadParagraph": "<p class='lead'>Engaging, enthusiastic introduction paragraph...</p>",
      "objectivesCard": "<div class='card'><h2>🎯 What You'll Learn</h2><p>By the end of this lesson, you'll be able to:</p><ul><li>...</li></ul></div>",
      "universalCard": "<div class='card' style='background: linear-gradient(135deg, #667eea 0%, #764ba2 100%); color: white;'><h3 style='color: white; margin-top: 0;'>🌍 Universal Topic</h3>...<ul style='columns: 2; column-gap: 2rem;'><li>✅ Software</li>...</ul></div>",
      "contextCard": "Optional: <div class='card' style='background: #fff3e0;'><h3>💡 Why Topic Matters</h3><h4 style='color: #d32f2f;'>❌ Without</h4>...<h4 style='color: #2e7d32;'>✅ With</h4>...</div>",
      "headerClose": "</header>"
    },
    "tableOfContentsStructure": "<nav class='card' aria-label='Table of Contents'><h2 style='cursor: pointer; user-select: none; display: flex; justify-content: space-between; align-items: center;' onclick='toggleTOC()'><span>📑 Table of Contents</span><span id='toc-toggle-icon' style='transition: transform 0.3s;'>▼</span></h2><ol id='toc-list' style='overflow: hidden; transition: max-height 0.3s ease-out; max-height: 1000px; margin: 0; padding-left: 1.5rem;'><li><a href='#id' class='toc-link'>Title</a></li>...</ol></nav>",
    "contentSections": {
      "sectionWrapper": "<section id='kebab-case-id' class='lesson-section'>",
      "sectionTitle": "<h2>Title With Emoji 🎯</h2>",
      "subsectionTitle": "<h3>Subsection Title</h3>",
      "cards": "<div class='card'> for grouped content",
      "gradientCards": "style='background: linear-gradient(135deg, color1, color2); color: white;' for emphasis",
      "coloredCards": "style='background: #e3f2fd;' (blue info), #fff3e0 (orange warning/context), #e8f5e9 (green success), #ffebee (red alert)",
      "tables": "Use <table> for comparisons and structured data",
      "blockquotes": "<blockquote><strong>💡 Pro Tip:</strong> content</blockquote>",
      "mermaidDiagrams": "<div class='mermaid'>graph TD...</div>",
      "codeBlocks": "<div class='code-block'><pre><code>...</code></pre></div>"
    },
    "closingStructure": {
      "requiredElements": ["Summary section", "Resources section", "Lesson navigation", "</div> (container)", "</main>", "<script src='js/clipboard.js'></script>", "<script src='js/course-enhancements.js'></script>", "</body>", "</html>"]
    },
    "criticalClassNames": {
      "CORRECT": {
        "skipLink": "skip-to-main",
        "navLogo": "nav-logo",
        "sectionClass": "lesson-section",
        "tocLink": "toc-link"
      },
      "WRONG_DO_NOT_USE": {
        "skipLink": "skip-link",
        "navLogo": "logo",
        "sectionClass": "content-section"
      }
    },
    "criticalReminders": [
      "ALWAYS check existing complete lessons for exact structure before creating new lessons",
      "Use class='lesson-section' NOT class='content-section'",
      "Use class='nav-logo' NOT class='logo'",
      "Use class='skip-to-main' NOT class='skip-link'",
      "Breadcrumb uses <ul><li> NOT <ol>",
      "Fragment A includes ALL opening structure through first 1-3 sections",
      "Middle fragments have NO DOCTYPE, HEAD, or BODY tags - content only",
      "Final fragment includes ALL closing tags"
    ]
  }
}
